[
 {
  "absolute_value": 0,
  "align_labels_right": 0,
  "css": null,
  "custom_format": 0,
  "default_print_language": "ar",
  "disabled": 0,
  "doc_type": "Sales Invoice",
  "docstatus": 0,
  "doctype": "Print Format",
  "font": null,
  "font_size": 14,
  "format_data": null,
  "html": null,
  "line_breaks": 0,
  "margin_bottom": 15.0,
  "margin_left": 15.0,
  "margin_right": 15.0,
  "margin_top": 15.0,
  "modified": "2025-12-26 01:09:20.411196",
  "module": "dms_plus",
  "name": "فاتورة ضريبية-DMS",
  "page_number": "Hide",
  "pdf_generator": "wkhtmltopdf",
  "print_designer": 0,
  "print_designer_after_table": null,
  "print_designer_body": null,
  "print_designer_footer": null,
  "print_designer_header": null,
  "print_designer_preview_img": null,
  "print_designer_print_format": null,
  "print_designer_settings": null,
  "print_designer_template_app": "print_designer",
  "print_format_builder": 0,
  "print_format_builder_beta": 0,
  "print_format_for": "DocType",
  "print_format_type": "Jinja",
  "raw_commands": null,
  "raw_printing": 0,
  "report": null,
  "show_section_headings": 0,
  "standard": "Yes"
 },
 {
  "absolute_value": 0,
  "align_labels_right": 1,
  "css": null,
  "custom_format": 0,
  "default_print_language": "en",
  "disabled": 0,
  "doc_type": "Sales Invoice",
  "docstatus": 0,
  "doctype": "Print Format",
  "font": null,
  "font_size": 14,
  "format_data": null,
  "html": null,
  "line_breaks": 1,
  "margin_bottom": 15.0,
  "margin_left": 15.0,
  "margin_right": 15.0,
  "margin_top": 15.0,
  "modified": "2025-12-26 01:13:03.990328",
  "module": "dms_plus",
  "name": "Tax Invoice-DMS",
  "page_number": "Hide",
  "pdf_generator": "wkhtmltopdf",
  "print_designer": 0,
  "print_designer_after_table": null,
  "print_designer_body": null,
  "print_designer_footer": null,
  "print_designer_header": null,
  "print_designer_preview_img": null,
  "print_designer_print_format": null,
  "print_designer_settings": null,
  "print_designer_template_app": "print_designer",
  "print_format_builder": 0,
  "print_format_builder_beta": 0,
  "print_format_for": "DocType",
  "print_format_type": "Jinja",
  "raw_commands": null,
  "raw_printing": 0,
  "report": null,
  "show_section_headings": 1,
  "standard": "Yes"
 },
 {
  "absolute_value": 0,
  "align_labels_right": 0,
  "css": null,
  "custom_format": 0,
  "default_print_language": "ar",
  "disabled": 0,
  "doc_type": "Sales Invoice",
  "docstatus": 0,
  "doctype": "Print Format",
  "font": null,
  "font_size": 14,
  "format_data": null,
  "html": null,
  "line_breaks": 0,
  "margin_bottom": 15.0,
  "margin_left": 15.0,
  "margin_right": 15.0,
  "margin_top": 15.0,
  "modified": "2025-12-26 01:18:42.406277",
  "module": "dms_plus",
  "name": "فاتورة أولية -DMS",
  "page_number": "Hide",
  "pdf_generator": "wkhtmltopdf",
  "print_designer": 0,
  "print_designer_after_table": null,
  "print_designer_body": null,
  "print_designer_footer": null,
  "print_designer_header": null,
  "print_designer_preview_img": null,
  "print_designer_print_format": null,
  "print_designer_settings": null,
  "print_designer_template_app": "print_designer",
  "print_format_builder": 0,
  "print_format_builder_beta": 0,
  "print_format_for": "DocType",
  "print_format_type": "Jinja",
  "raw_commands": null,
  "raw_printing": 0,
  "report": null,
  "show_section_headings": 0,
  "standard": "Yes"
 },
 {
  "absolute_value": 0,
  "align_labels_right": 1,
  "css": null,
  "custom_format": 0,
  "default_print_language": "en",
  "disabled": 0,
  "doc_type": "Sales Invoice",
  "docstatus": 0,
  "doctype": "Print Format",
  "font": null,
  "font_size": 14,
  "format_data": null,
  "html": null,
  "line_breaks": 1,
  "margin_bottom": 15.0,
  "margin_left": 15.0,
  "margin_right": 15.0,
  "margin_top": 15.0,
  "modified": "2025-12-26 01:21:41.714901",
  "module": "dms_plus",
  "name": "Proforma Invoice-DMS",
  "page_number": "Hide",
  "pdf_generator": "wkhtmltopdf",
  "print_designer": 0,
  "print_designer_after_table": null,
  "print_designer_body": null,
  "print_designer_footer": null,
  "print_designer_header": null,
  "print_designer_preview_img": null,
  "print_designer_print_format": null,
  "print_designer_settings": null,
  "print_designer_template_app": "print_designer",
  "print_format_builder": 0,
  "print_format_builder_beta": 0,
  "print_format_for": "DocType",
  "print_format_type": "Jinja",
  "raw_commands": null,
  "raw_printing": 0,
  "report": null,
  "show_section_headings": 1,
  "standard": "Yes"
 },
 {
  "absolute_value": 0,
  "align_labels_right": 0,
  "css": null,
  "custom_format": 0,
  "default_print_language": "ar",
  "disabled": 0,
  "doc_type": "Quotation",
  "docstatus": 0,
  "doctype": "Print Format",
  "font": null,
  "font_size": 14,
  "format_data": null,
  "html": null,
  "line_breaks": 1,
  "margin_bottom": 15.0,
  "margin_left": 15.0,
  "margin_right": 15.0,
  "margin_top": 0.0,
  "modified": "2026-01-05 00:59:35.089095",
  "module": "dms_plus",
  "name": "عرض سعر - DMS",
  "page_number": "Top Center",
  "pdf_generator": "wkhtmltopdf",
  "print_designer": 0,
  "print_designer_after_table": null,
  "print_designer_body": null,
  "print_designer_footer": null,
  "print_designer_header": null,
  "print_designer_preview_img": null,
  "print_designer_print_format": null,
  "print_designer_settings": null,
  "print_designer_template_app": "print_designer",
  "print_format_builder": 0,
  "print_format_builder_beta": 0,
  "print_format_for": "DocType",
  "print_format_type": "Jinja",
  "raw_commands": null,
  "raw_printing": 0,
  "report": null,
  "show_section_headings": 1,
  "standard": "Yes"
 },
 {
  "absolute_value": 0,
  "align_labels_right": 1,
  "css": null,
  "custom_format": 0,
  "default_print_language": "en",
  "disabled": 0,
  "doc_type": "Quotation",
  "docstatus": 0,
  "doctype": "Print Format",
  "font": null,
  "font_size": 14,
  "format_data": null,
  "html": null,
  "line_breaks": 1,
  "margin_bottom": 15.0,
  "margin_left": 15.0,
  "margin_right": 15.0,
  "margin_top": 15.0,
  "modified": "2025-12-28 01:09:09.641351",
  "module": "dms_plus",
  "name": "Quotation - DMS",
  "page_number": "Bottom Center",
  "pdf_generator": "chrome",
  "print_designer": 0,
  "print_designer_after_table": null,
  "print_designer_body": null,
  "print_designer_footer": null,
  "print_designer_header": null,
  "print_designer_preview_img": null,
  "print_designer_print_format": null,
  "print_designer_settings": null,
  "print_designer_template_app": "print_designer",
  "print_format_builder": 0,
  "print_format_builder_beta": 0,
  "print_format_for": "DocType",
  "print_format_type": "Jinja",
  "raw_commands": null,
  "raw_printing": 0,
  "report": null,
  "show_section_headings": 1,
  "standard": "Yes"
 },
 {
  "absolute_value": 0,
  "align_labels_right": 1,
  "css": null,
  "custom_format": 0,
  "default_print_language": "en",
  "disabled": 0,
  "doc_type": "Sales Invoice",
  "docstatus": 0,
  "doctype": "Print Format",
  "font": null,
  "font_size": 14,
  "format_data": null,
  "html": null,
  "line_breaks": 1,
  "margin_bottom": 15.0,
  "margin_left": 15.0,
  "margin_right": 15.0,
  "margin_top": 15.0,
  "modified": "2025-11-30 15:50:32.268668",
  "module": "dms_plus",
  "name": "Tax Invoice DMS",
  "page_number": "Hide",
  "pdf_generator": "wkhtmltopdf",
  "print_designer": 0,
  "print_designer_after_table": null,
  "print_designer_body": null,
  "print_designer_footer": null,
  "print_designer_header": null,
  "print_designer_preview_img": null,
  "print_designer_print_format": null,
  "print_designer_settings": null,
  "print_designer_template_app": "print_designer",
  "print_format_builder": 0,
  "print_format_builder_beta": 0,
  "print_format_for": null,
  "print_format_type": "Jinja",
  "raw_commands": null,
  "raw_printing": 0,
  "report": null,
  "show_section_headings": 1,
  "standard": "Yes"
 }
]